binalyzer_template_provider/__init__.py
binalyzer_template_provider/extension.py
binalyzer_template_provider/xml.py
binalyzer_template_provider/generated/XMLLexer.py
binalyzer_template_provider/generated/XMLParser.py
binalyzer_template_provider/generated/XMLParserListener.py
binalyzer_template_provider/generated/__init__.py
binalyzer_template_provider-1.0.3.data/data/CHANGELOG.md
binalyzer_template_provider-1.0.3.dist-info/AUTHORS
binalyzer_template_provider-1.0.3.dist-info/LICENSE.rst
binalyzer_template_provider-1.0.3.dist-info/METADATA
binalyzer_template_provider-1.0.3.dist-info/WHEEL
binalyzer_template_provider-1.0.3.dist-info/top_level.txt
binalyzer_template_provider-1.0.3.dist-info/RECORD
