Metadata-Version: 2.1
Name: binalyzer-template-provider
Version: 1.0.3
Summary: Binary Data Analyzer
Home-page: https://binalyzer.denisvasilik.com
Author: Denis Vasilìk
Author-email: contact@denisvasilik.com
Project-URL: Bug Tracker, https://github.com/denisvasilik/binalyzer/issues
Project-URL: Documentation, https://binalyzer.readthedocs.io/en/latest/
Project-URL: Source Code, https://github.com/denisvasilik/binalyzer/
Classifier: Programming Language :: Python :: 3.6
Classifier: Operating System :: POSIX :: Linux
License-File: LICENSE.rst
License-File: AUTHORS
Requires-Dist: antlr4-python3-runtime (==4.8)
Requires-Dist: anytree (>=2.8.0)
Requires-Dist: requests (>=2.25.1)
